{
  "arch": "DINOv2-ViT-S/14",
  "mode": "stage5",
  "run_name": "LabelSmoothing",
  "seed": 42,
  "source_weights": "DINOv2-pretrained",
  "input_resolution": "224x224",
  "patch_tokens": 256,
  "ablation": "label_smoothing (train-CE, 0.1) vs dino_combined_Game6boosted (plain CE); single variable",
  "label_smoothing_train_ce": 0.1,
  "eval_criterion": "plain CrossEntropyLoss (label_smoothing=0.0)",
  "optimizer": "AdamW",
  "betas": [0.9, 0.999],
  "weight_decay": 0.05,
  "lr_schedule": "cosine, eta_min=0.01*lr_head, T_max=18",
  "lr_head": 0.0001,
  "lr_backbone": 1e-05,
  "epochs": 20,
  "warmup_phaseA_epochs": 2,
  "early_stop_patience": 0,
  "batch_size": 32,
  "grad_accum": 2,
  "effective_batch": 64,
  "compute_note": "GTX 1080 Ti (11 GiB; RTX 3090 unavailable this session). grad-accum 32x2 = effective batch 64; optimizer-steps-per-epoch 1563 == combined_game6's batch-64 steps (config-identity gate asserted). LayerNorm-only model -> numerically equivalent to batch 64.",
  "sampler": "combined: WeightedRandomSampler 50/50 synth/real, 100k draws/epoch",
  "augmentation": "jitter@0.7 -> shear@0.8(±8°) -> noise@0.5(std=0.015)",
  "selection_metric": "game2_real_val",
  "selected_epoch": 15,
  "data": "dataset_v1 synth + 30 manual (games 8-11) + game4 + game5 + game6 PGN (combined)",
  "split": {
    "train_manual_games": [8, 9, 10, 11],
    "train_pgn_games": [4, 5, 6],
    "val_game": "game2",
    "test_games": [7]
  },
  "results": {
    "heldout_per_square": 0.9824,
    "heldout_piece_only": 0.9632,
    "heldout_empty": 0.9979,
    "heldout_games": [7],
    "val_game": "game2",
    "val_per_square": 0.9953,
    "val_piece_only": 0.9880,
    "forgetting_delta": 0.3525
  },
  "note": "recipe.json reconstructed post-hoc: the run completed all 20 epochs and saved all results/predictions/plots, but a leftover diag-confound block (assumed best_game7_diag.pt, absent under --diag_game7 0) raised FileNotFoundError before the trainer's own Cell 16 recipe write. The trainer has since been fixed (confound block gated on diag_game7). Values here are from the run log + labelsmooth_vs_combined_compare.json."
}
